
[
    {
      "SKU": "6762e75b-fcea-4a56-a9d4-dcd59a437feb",
      "PRODUCT": "Awesome Steel Gloves",
      "CATEGORY": "Licensed",
      "PRICE": 78215,
      "STOCK": 38847,
      "STATUS": true,
      "DISCOUNT": 49963,
      "PUBLISHED": true,
      "id": "1"
    },
    {
      "SKU": "01db4473-bee0-469e-ae35-63fed039bca3",
      "PRODUCT": "Awesome Wooden Table",
      "CATEGORY": "Awesome",
      "PRICE": 8163,
      "STOCK": 58132,
      "STATUS": true,
      "DISCOUNT": 66325,
      "PUBLISHED": true,
      "id": "2"
    },
    {
      "SKU": "181400aa-59f5-41e4-8815-49e7216fff90",
      "PRODUCT": "Gorgeous Concrete Sausages",
      "CATEGORY": "Gorgeous",
      "PRICE": 2988,
      "STOCK": 92120,
      "STATUS": false,
      "DISCOUNT": 43790,
      "PUBLISHED": false,
      "id": "3"
    },
    {
      "SKU": "d8705946-e5f0-446f-bd8c-fddbf81b57e4",
      "PRODUCT": "Gorgeous Plastic Sausages",
      "CATEGORY": "Handcrafted",
      "PRICE": 60835,
      "STOCK": 32730,
      "STATUS": false,
      "DISCOUNT": 81790,
      "PUBLISHED": true,
      "id": "4"
    },
    {
      "SKU": "f04cc303-4c5c-4ddf-9b4f-8682b2fc100a",
      "PRODUCT": "Practical Wooden Salad",
      "CATEGORY": "Small",
      "PRICE": 33419,
      "STOCK": 38682,
      "STATUS": true,
      "DISCOUNT": 79766,
      "PUBLISHED": false,
      "id": "5"
    },
    {
      "SKU": "dceb7cac-add6-4a53-a1f9-0898a79ac529",
      "PRODUCT": "Gorgeous Plastic Table",
      "CATEGORY": "Ergonomic",
      "PRICE": 73624,
      "STOCK": 48408,
      "STATUS": false,
      "DISCOUNT": 76913,
      "PUBLISHED": false,
      "id": "6"
    },
    {
      "SKU": "78b44476-7118-42e0-a5e9-0b454ebe5c46",
      "PRODUCT": "Incredible Frozen Chair",
      "CATEGORY": "Ergonomic",
      "PRICE": 61101,
      "STOCK": 54728,
      "STATUS": true,
      "DISCOUNT": 34745,
      "PUBLISHED": false,
      "id": "7"
    },
    {
      "SKU": "266c9761-8b29-4235-870c-a48c8fb48fbb",
      "PRODUCT": "Fantastic Concrete Mouse",
      "CATEGORY": "Ergonomic",
      "PRICE": 99974,
      "STOCK": 16732,
      "STATUS": true,
      "DISCOUNT": 22596,
      "PUBLISHED": true,
      "id": "8"
    },
    {
      "SKU": "98d8d58b-1fa8-4b64-b26a-fce5cf68d19e",
      "PRODUCT": "Practical Wooden Car",
      "CATEGORY": "Licensed",
      "PRICE": 85869,
      "STOCK": 73093,
      "STATUS": true,
      "DISCOUNT": 68640,
      "PUBLISHED": true,
      "id": "9"
    },
    {
      "SKU": "ef5a8a5e-04f8-4662-92ff-3d12165f110a",
      "PRODUCT": "Rustic Metal Keyboard",
      "CATEGORY": "Intelligent",
      "PRICE": 47198,
      "STOCK": 74774,
      "STATUS": true,
      "DISCOUNT": 1425,
      "PUBLISHED": true,
      "id": "10"
    },
    {
      "SKU": "8f7c713c-f039-4143-a4aa-5a6f7f407e2f",
      "PRODUCT": "Practical Steel Tuna",
      "CATEGORY": "Practical",
      "PRICE": 21206,
      "STOCK": 12388,
      "STATUS": true,
      "DISCOUNT": 78462,
      "PUBLISHED": false,
      "id": "11"
    },
    {
      "SKU": "e4ddd69a-6d58-41f8-954b-f2c94ccac670",
      "PRODUCT": "Gorgeous Soft Chips",
      "CATEGORY": "Refined",
      "PRICE": 9516,
      "STOCK": 63190,
      "STATUS": false,
      "DISCOUNT": 809,
      "PUBLISHED": true,
      "id": "12"
    },
    {
      "SKU": "1af769a1-18ee-4ab7-b35f-68812ea397e5",
      "PRODUCT": "Generic Metal Hat",
      "CATEGORY": "Generic",
      "PRICE": 29470,
      "STOCK": 30190,
      "STATUS": true,
      "DISCOUNT": 73390,
      "PUBLISHED": true,
      "id": "13"
    },
    {
      "SKU": "c3cc3501-d994-4d64-b381-f09b66a67e89",
      "PRODUCT": "Fantastic Fresh Tuna",
      "CATEGORY": "Handcrafted",
      "PRICE": 92754,
      "STOCK": 54819,
      "STATUS": true,
      "DISCOUNT": 19333,
      "PUBLISHED": false,
      "id": "14"
    },
    {
      "SKU": "ed19a96f-d860-483d-bce3-221925d36650",
      "PRODUCT": "Rustic Soft Bacon",
      "CATEGORY": "Awesome",
      "PRICE": 3747,
      "STOCK": 24655,
      "STATUS": false,
      "DISCOUNT": 78849,
      "PUBLISHED": false,
      "id": "15"
    },
    {
      "SKU": "2b4a105d-42b5-4ea8-b693-71c5e7636bc3",
      "PRODUCT": "Intelligent Plastic Sausages",
      "CATEGORY": "Tasty",
      "PRICE": 93583,
      "STOCK": 36576,
      "STATUS": false,
      "DISCOUNT": 41028,
      "PUBLISHED": true,
      "id": "16"
    },
    {
      "SKU": "3c5c98c1-6b6c-4eea-9842-e2e82a4c5dff",
      "PRODUCT": "Ergonomic Cotton Shoes",
      "CATEGORY": "Licensed",
      "PRICE": 60510,
      "STOCK": 33258,
      "STATUS": true,
      "DISCOUNT": 5767,
      "PUBLISHED": true,
      "id": "17"
    },
    {
      "SKU": "80873a6b-2124-420b-8466-1cf12f0bed78",
      "PRODUCT": "Intelligent Frozen Salad",
      "CATEGORY": "Incredible",
      "PRICE": 81425,
      "STOCK": 72675,
      "STATUS": true,
      "DISCOUNT": 19080,
      "PUBLISHED": false,
      "id": "18"
    },
    {
      "SKU": "ed24fed8-becd-497b-acc8-91d22a1fcdb7",
      "PRODUCT": "Gorgeous Cotton Chicken",
      "CATEGORY": "Tasty",
      "PRICE": 32582,
      "STOCK": 91322,
      "STATUS": false,
      "DISCOUNT": 93524,
      "PUBLISHED": true,
      "id": "19"
    },
    {
      "SKU": "214bca4a-bd3b-42d3-836e-eeee443a5c80",
      "PRODUCT": "Generic Wooden Gloves",
      "CATEGORY": "Generic",
      "PRICE": 43814,
      "STOCK": 97220,
      "STATUS": false,
      "DISCOUNT": 58358,
      "PUBLISHED": true,
      "id": "20"
    },
    {
      "SKU": "6e387e03-686a-485d-af7d-d4386ab22e8d",
      "PRODUCT": "Generic Soft Chair",
      "CATEGORY": "Tasty",
      "PRICE": 71113,
      "STOCK": 10219,
      "STATUS": false,
      "DISCOUNT": 88813,
      "PUBLISHED": true,
      "id": "21"
    },
    {
      "SKU": "16501113-d4ea-4fad-bff2-6c986aca72c2",
      "PRODUCT": "Ergonomic Cotton Bacon",
      "CATEGORY": "Practical",
      "PRICE": 61878,
      "STOCK": 23961,
      "STATUS": true,
      "DISCOUNT": 55955,
      "PUBLISHED": false,
      "id": "22"
    },
    {
      "SKU": "bcb93140-2d35-4105-9b28-b96a8c4724c1",
      "PRODUCT": "Rustic Metal Shirt",
      "CATEGORY": "Intelligent",
      "PRICE": 844,
      "STOCK": 87877,
      "STATUS": false,
      "DISCOUNT": 22801,
      "PUBLISHED": false,
      "id": "23"
    },
    {
      "SKU": "23581d58-c5c9-4863-a7ba-efa817722800",
      "PRODUCT": "Tasty Wooden Pizza",
      "CATEGORY": "Awesome",
      "PRICE": 37909,
      "STOCK": 8855,
      "STATUS": false,
      "DISCOUNT": 7596,
      "PUBLISHED": false,
      "id": "24"
    },
    {
      "SKU": "d7354e03-a27d-4f71-bddd-b18fd7944054",
      "PRODUCT": "Small Granite Sausages",
      "CATEGORY": "Awesome",
      "PRICE": 44232,
      "STOCK": 54637,
      "STATUS": false,
      "DISCOUNT": 85108,
      "PUBLISHED": true,
      "id": "25"
    },
    {
      "SKU": "de59aba4-602b-429f-a79d-99f393217e38",
      "PRODUCT": "Sleek Rubber Cheese",
      "CATEGORY": "Licensed",
      "PRICE": 63042,
      "STOCK": 42799,
      "STATUS": true,
      "DISCOUNT": 9930,
      "PUBLISHED": false,
      "id": "26"
    },
    {
      "SKU": "f2723394-4b4b-4e7d-91cb-1cd4e57dbdfc",
      "PRODUCT": "Fantastic Fresh Hat",
      "CATEGORY": "Generic",
      "PRICE": 90808,
      "STOCK": 95890,
      "STATUS": true,
      "DISCOUNT": 91811,
      "PUBLISHED": true,
      "id": "27"
    },
    {
      "SKU": "7dccb8d0-9153-4aed-8f20-a86487e65052",
      "PRODUCT": "Generic Fresh Bike",
      "CATEGORY": "Practical",
      "PRICE": 88116,
      "STOCK": 61990,
      "STATUS": true,
      "DISCOUNT": 80858,
      "PUBLISHED": false,
      "id": "28"
    },
    {
      "SKU": "62a63d4f-32bc-4cd7-992b-85f0b749431a",
      "PRODUCT": "Generic Metal Chair",
      "CATEGORY": "Sleek",
      "PRICE": 15398,
      "STOCK": 57529,
      "STATUS": true,
      "DISCOUNT": 3118,
      "PUBLISHED": false,
      "id": "29"
    },
    {
      "SKU": "e40996f5-892c-469b-88b2-3028bf3ed875",
      "PRODUCT": "Licensed Frozen Car",
      "CATEGORY": "Gorgeous",
      "PRICE": 40904,
      "STOCK": 74577,
      "STATUS": false,
      "DISCOUNT": 84310,
      "PUBLISHED": true,
      "id": "30"
    },
    {
      "SKU": "9a43776e-0f3f-44ea-9b3e-5994d148e121",
      "PRODUCT": "Handmade Cotton Cheese",
      "CATEGORY": "Tasty",
      "PRICE": 58368,
      "STOCK": 43270,
      "STATUS": true,
      "DISCOUNT": 30483,
      "PUBLISHED": false,
      "id": "31"
    },
    {
      "SKU": "5bbc100d-c278-4db2-bb48-432e13dce92e",
      "PRODUCT": "Awesome Steel Fish",
      "CATEGORY": "Incredible",
      "PRICE": 68377,
      "STOCK": 16791,
      "STATUS": true,
      "DISCOUNT": 23400,
      "PUBLISHED": true,
      "id": "32"
    },
    {
      "SKU": "2d4c875d-6d8f-4ccb-b2ac-553ca0151b34",
      "PRODUCT": "Incredible Frozen Car",
      "CATEGORY": "Tasty",
      "PRICE": 77644,
      "STOCK": 60262,
      "STATUS": true,
      "DISCOUNT": 17749,
      "PUBLISHED": false,
      "id": "33"
    },
    {
      "SKU": "a6b8aa7c-716b-4e3b-a486-f6e837dae8ef",
      "PRODUCT": "Gorgeous Fresh Tuna",
      "CATEGORY": "Intelligent",
      "PRICE": 88837,
      "STOCK": 26537,
      "STATUS": false,
      "DISCOUNT": 86029,
      "PUBLISHED": true,
      "id": "34"
    },
    {
      "SKU": "2399e297-3603-47d0-88f9-14e7c20ea1e1",
      "PRODUCT": "Refined Metal Gloves",
      "CATEGORY": "Unbranded",
      "PRICE": 68660,
      "STOCK": 11007,
      "STATUS": false,
      "DISCOUNT": 3599,
      "PUBLISHED": false,
      "id": "35"
    },
    {
      "SKU": "7ad87d85-57f6-4482-be94-cfda58d91ed6",
      "PRODUCT": "Incredible Plastic Chicken",
      "CATEGORY": "Sleek",
      "PRICE": 43816,
      "STOCK": 3114,
      "STATUS": true,
      "DISCOUNT": 53903,
      "PUBLISHED": false,
      "id": "36"
    },
    {
      "SKU": "20d6dac7-83f0-48ac-980e-124cd1ac594b",
      "PRODUCT": "Licensed Rubber Keyboard",
      "CATEGORY": "Handmade",
      "PRICE": 19342,
      "STOCK": 95999,
      "STATUS": false,
      "DISCOUNT": 25029,
      "PUBLISHED": false,
      "id": "37"
    },
    {
      "SKU": "56ce608a-1d88-4e27-910e-67013f353479",
      "PRODUCT": "Intelligent Steel Chicken",
      "CATEGORY": "Handcrafted",
      "PRICE": 13221,
      "STOCK": 51067,
      "STATUS": true,
      "DISCOUNT": 9256,
      "PUBLISHED": false,
      "id": "38"
    },
    {
      "SKU": "899b9a42-a04d-4f79-981c-d1d6599e7a68",
      "PRODUCT": "Generic Plastic Cheese",
      "CATEGORY": "Refined",
      "PRICE": 79180,
      "STOCK": 39079,
      "STATUS": true,
      "DISCOUNT": 66833,
      "PUBLISHED": true,
      "id": "39"
    },
    {
      "SKU": "782e512b-bc4a-448f-aa00-8f38a47a33b7",
      "PRODUCT": "Tasty Granite Car",
      "CATEGORY": "Tasty",
      "PRICE": 99009,
      "STOCK": 64637,
      "STATUS": false,
      "DISCOUNT": 54323,
      "PUBLISHED": false,
      "id": "40"
    },
    {
      "SKU": "ed463e38-3244-482f-a563-383f3da5d37d",
      "PRODUCT": "Refined Plastic Computer",
      "CATEGORY": "Gorgeous",
      "PRICE": 36175,
      "STOCK": 47798,
      "STATUS": true,
      "DISCOUNT": 71590,
      "PUBLISHED": true,
      "id": "41"
    },
    {
      "SKU": "1921db22-12a2-48be-922d-3fb2fc0ea448",
      "PRODUCT": "Licensed Metal Table",
      "CATEGORY": "Gorgeous",
      "PRICE": 79838,
      "STOCK": 19510,
      "STATUS": true,
      "DISCOUNT": 60218,
      "PUBLISHED": true,
      "id": "42"
    },
    {
      "SKU": "b3bf564f-41df-4894-aaa5-a0106a2a9383",
      "PRODUCT": "Intelligent Wooden Bacon",
      "CATEGORY": "Fantastic",
      "PRICE": 54891,
      "STOCK": 51959,
      "STATUS": true,
      "DISCOUNT": 19580,
      "PUBLISHED": false,
      "id": "43"
    },
    {
      "SKU": "c5fb489c-e86f-4fdb-9d75-3c876234d081",
      "PRODUCT": "Ergonomic Wooden Table",
      "CATEGORY": "Incredible",
      "PRICE": 90758,
      "STOCK": 5726,
      "STATUS": true,
      "DISCOUNT": 67985,
      "PUBLISHED": true,
      "id": "44"
    },
    {
      "SKU": "7c930c88-8baf-4073-a614-aa58b9fbc15b",
      "PRODUCT": "Fantastic Rubber Salad",
      "CATEGORY": "Small",
      "PRICE": 95080,
      "STOCK": 50876,
      "STATUS": false,
      "DISCOUNT": 60883,
      "PUBLISHED": false,
      "id": "45"
    }
  ] 